setup.cfg
setup.py
protector/__init__.py
protector/__main__.py
protector/daemon.py
protector/protector_main.py
protector/version.py
protector.egg-info/PKG-INFO
protector.egg-info/SOURCES.txt
protector.egg-info/dependency_links.txt
protector.egg-info/entry_points.txt
protector.egg-info/not-zip-safe
protector.egg-info/requires.txt
protector.egg-info/top_level.txt
protector/config/__init__.py
protector/config/default_config.py
protector/config/loader.py
protector/config/object_view.py
protector/config/smart_formatter.py
protector/guard/__init__.py
protector/guard/guard.py
protector/influxdb/__init__.py
protector/influxdb/daterange.py
protector/influxdb/keyword.py
protector/influxdb/resolution.py
protector/influxdb/time_expression.py
protector/parser/__init__.py
protector/parser/query_parser.py
protector/parser/subparsers/__init__.py
protector/parser/subparsers/datapoints.py
protector/parser/subparsers/duration.py
protector/parser/subparsers/resolution.py
protector/parser/subparsers/time_range.py
protector/proxy/__init__.py
protector/proxy/http_request.py
protector/proxy/request_handler.py
protector/proxy/server.py
protector/query/__init__.py
protector/query/delete.py
protector/query/drop.py
protector/query/list.py
protector/query/query.py
protector/query/select.py
protector/rules/__init__.py
protector/rules/loader.py
protector/rules/negative_groupby_statement.py
protector/rules/prevent_delete.py
protector/rules/prevent_drop.py
protector/rules/query_old_data.py
protector/rules/rule.py
protector/rules/rule_list.py
protector/rules/series_endswith_dot.py
protector/rules/short_series_name.py
protector/rules/too_many_datapoints.py
protector/sanitizer/__init__.py
protector/sanitizer/sanitizer.py
protector/tests/__init__.py
protector/tests/config_test/__init__.py
protector/tests/config_test/test_loader.py
protector/tests/daemon_test/__init__.py
protector/tests/daemon_test/test_daemon.py
protector/tests/fixtures/__init__.py
protector/tests/fixtures/loader.py
protector/tests/guard_test/__init__.py
protector/tests/guard_test/test_guard.py
protector/tests/parser_test/__init__.py
protector/tests/parser_test/test_parse_query_delete.py
protector/tests/parser_test/test_parse_query_drop.py
