Metadata-Version: 1.1
Name: protector
Version: 0.6.0
Summary: A circuit breaker for Time series databases like InfluxDB that prevents expensive queries
Home-page: http://github.com/trivago/protector
Author: Matthias Endler
Author-email: matthias.endler@trivago.com
License: BSD
Keywords: influxdb proxy graphite circuit-breaker
Platform: UNKNOWN
Classifier: Development Status :: 4 - Beta
Classifier: License :: OSI Approved :: BSD License
Classifier: Topic :: Utilities
Classifier: Programming Language :: Python
Classifier: Programming Language :: Python :: 2
Classifier: Programming Language :: Python :: 2.6
Classifier: Programming Language :: Python :: 2.7
Classifier: Programming Language :: Python :: Implementation :: PyPy
